setup.py
aws_fed.egg-info/PKG-INFO
aws_fed.egg-info/SOURCES.txt
aws_fed.egg-info/dependency_links.txt
aws_fed.egg-info/entry_points.txt
aws_fed.egg-info/top_level.txt
awsfed/__init__.py
awsfed/__main__.py
awsfed/awsfed.py