Metadata-Version: 1.0
Name: aws-fed
Version: 0.0.1
Summary: Creates a temporary AWS federated token from an iam role.
Home-page: https://github.com/komoot/aws-fed
Author: Jan Heuer
Author-email: jan@komoot.de
License: UNKNOWN
Platform: UNKNOWN
